Workbook

Sheet shopping_behavior_updated
A1: customer_id | B1: customer_age | C1: customer_gender | D1: product_id | E1: product_item | F1: product_category | G1: purchase_id | H1: _purchase_id | I1: purchase_amount | J1: customer_location | K1: product_size | L1: product_colour | M1: product_season | N1: product_rating | O1: customer_subscription | P1: purchase_shipping type | Q1: purchase_discount | R1: purchase_promocode | S1: customer_purchase count | T1: purchase_payment type | U1: customer_purchase frequency | V1: purchase_date | W1: Total_Purchase_Count | X1: Total_Spend | Y1: Subscription_status | Z1: Persona
A2: 1 | B2: 55 | C2: Male | D2: 1 | E2: Blouse | F2: Clothing | G2: 1 | H2: 200 | I2: 53 | J2: Kentucky | K2: L | L2: Gray | M2: Winter | N2: 3.1 | O2: 1 | P2: Express | Q2: Yes | R2: Yes | S2: 14 | T2: Venmo | U2: Fortnightly | V2: 45338 | W2: =Table1[[#This Row],[customer_purchase count]]+1 -> 15 | X2: =Table1[[#This Row],[customer_purchase count]]*Rules!$B$3 -> 836.70103 | Y2: =IF(Table1[[#This Row],[customer_subscription]]=1,"Subscribed","Not Subscribed") -> Subscribed
A3: 2 | B3: 19 | C3: Male | D3: 2 | E3: Sweater | F3: Clothing | G3: 2 | H3: 201 | I3: 64 | J3: Maine | K3: L | L3: Maroon | M3: Winter | N3: 3.1 | O3: 1 | P3: Express | Q3: Yes | R3: Yes | S3: 2 | T3: Cash | U3: Fortnightly | V3: 45333 | W3: =Table1[[#This Row],[customer_purchase count]]+1 -> 3 | X3: =Table1[[#This Row],[customer_purchase count]]*Rules!$B$3 -> 119.52872 | Y3: =IF(Table1[[#This Row],[customer_subscription]]=1,"Subscribed","Not Subscribed") -> Subscribed
A4: 3 | B4: 50 | C4: Male | D4: 3 | E4: Jeans | F4: Clothing | G4: 3 | H4: 202 | I4: 73 | J4: Massachusetts | K4: S | L4: Maroon | M4: Spring | N4: 3.1 | O4: 1 | P4: Free Shipping | Q4: Yes | R4: Yes | S4: 23 | T4: Credit Card | U4: Weekly | V4: 45368 | W4: =Table1[[#This Row],[customer_purchase count]]+1 -> 24 | X4: =Table1[[#This Row],[customer_purchase count]]*Rules!$B$3 -> 1374.5803 | Y4: =IF(Table1[[#This Row],[customer_subscription]]=1,"Subscribed","Not Subscribed") -> Subscribed
A5: 4 | B5: 21 | C5: Male | D5: 4 | E5: Sandals | F5: Footwear | G5: 4 | H5: 203 | I5: 90 | J5: Rhode Island | K5: M | L5: Maroon | M5: Spring | N5: 3.5 | O5: 1 | P5: Next Day Air | Q5: Yes | R5: Yes | S5: 49 | T5: PayPal | U5: Weekly | V5: 45432 | W5: =Table1[[#This Row],[customer_purchase count]]+1 -> 50 | X5: =Table1[[#This Row],[customer_purchase count]]*Rules!$B$3 -> 2928.4536 | Y5: =IF(Table1[[#This Row],[customer_subscription]]=1,"Subscribed","Not Subscribed") -> Subscribed
A6: 5 | B6: 45 | C6: Male | D6: 5 | E6: Blouse | F6: Clothing | G6: 5 | H6: 205 | I6: 49 | J6: Oregon | K6: M | L6: Turquoise | M6: Spring | N6: 2.7 | O6: 1 | P6: Free Shipping | Q6: Yes | R6: Yes | S6: 31 | T6: PayPal | U6: Annually | V6: 45388 | W6: =Table1[[#This Row],[customer_purchase count]]+1 -> 32 | X6: =Table1[[#This Row],[customer_purchase count]]*Rules!$B$3 -> 1852.6951 | Y6: =IF(Table1[[#This Row],[customer_subscription]]=1,"Subscribed","Not Subscribed") -> Subscribed
A7: 6 | B7: 46 | C7: Male | D7: 6 | E7: Sneakers | F7: Footwear | G7: 6 | H7: 206 | I7: 20 | J7: Wyoming | K7: M | L7: White | M7: Summer | N7: 2.9 | O7: 1 | P7: Standard | Q7: Yes | R7: Yes | S7: 14 | T7: Venmo | U7: Weekly | V7: 45459 | W7: =Table1[[#This Row],[customer_purchase count]]+1 -> 15 | X7: =Table1[[#This Row],[customer_purchase count]]*Rules!$B$3 -> 836.70103 | Y7: =IF(Table1[[#This Row],[customer_subscription]]=1,"Subscribed","Not Subscribed") -> Subscribed
A8: 7 | B8: 63 | C8: Male | D8: 7 | E8: Shirt | F8: Clothing | G8: 7 | H8: 207 | I8: 85 | J8: Montana | K8: M | L8: Gray | M8: Fall | N8: 3.2 | O8: 1 | P8: Free Shipping | Q8: Yes | R8: Yes | S8: 49 | T8: Cash | U8: Quarterly | V8: 45591 | W8: =Table1[[#This Row],[customer_purchase count]]+1 -> 50 | X8: =Table1[[#This Row],[customer_purchase count]]*Rules!$B$3 -> 2928.4536 | Y8: =IF(Table1[[#This Row],[customer_subscription]]=1,"Subscribed","Not Subscribed") -> Subscribed
A9: 8 | B9: 27 | C9: Male | D9: 8 | E9: Shorts | F9: Clothing | G9: 8 | H9: 208 | I9: 34 | J9: Louisiana | K9: L | L9: Charcoal | M9: Winter | N9: 3.2 | O9: 1 | P9: Free Shipping | Q9: Yes | R9: Yes | S9: 19 | T9: Credit Card | U9: Weekly | V9: 45339 | W9: =Table1[[#This Row],[customer_purchase count]]+1 -> 20 | X9: =Table1[[#This Row],[customer_purchase count]]*Rules!$B$3 -> 1135.5228 | Y9: =IF(Table1[[#This Row],[customer_subscription]]=1,"Subscribed","Not Subscribed") -> Subscribed
A10: 9 | B10: 26 | C10: Male | D10: 9 | E10: Coat | F10: Outerwear | G10: 9 | H10: 209 | I10: 97 | J10: West Virginia | K10: L | L10: Silver | M10: Summer | N10: 2.6 | O10: 1 | P10: Express | Q10: Yes | R10: Yes | S10: 8 | T10: Venmo | U10: Annually | V10: 45531 | W10: =Table1[[#This Row],[customer_purchase count]]+1 -> 9 | X10: =Table1[[#This Row],[customer_purchase count]]*Rules!$B$3 -> 478.11487 | Y10: =IF(Table1[[#This Row],[customer_subscription]]=1,"Subscribed","Not Subscribed") -> Subscribed
A11: 10 | B11: 57 | C11: Male | D11: 10 | E11: Handbag | F11: Accessories | G11: 10 | H11: 211 | I11: 31 | J11: Missouri | K11: M | L11: Pink | M11: Spring | N11: 4.8 | O11: 1 | P11: 2-Day Shipping | Q11: Yes | R11: Yes | S11: 4 | T11: Cash | U11: Quarterly | V11: 45440 | W11: =Table1[[#This Row],[customer_purchase count]]+1 -> 5 | X11: =Table1[[#This Row],[customer_purchase count]]*Rules!$B$3 -> 239.05744 | Y11: =IF(Table1[[#This Row],[customer_subscription]]=1,"Subscribed","Not Subscribed") -> Subscribed
A12: 11 | B12: 53 | C12: Male | D12: 11 | E12: Shoes | F12: Footwear | G12: 11 | H12: 212 | I12: 34 | J12: Arkansas | K12: L | L12: Purple | M12: Fall | N12: 4.1 | O12: 1 | P12: Store Pickup | Q12: Yes | R12: Yes | S12: 26 | T12: Bank Transfer | U12: Bi-Weekly | V12: 45570 | W12: =Table1[[#This Row],[customer_purchase count]]+1 -> 27 | X12: =Table1[[#This Row],[customer_purchase count]]*Rules!$B$3 -> 1553.8733 | Y12: =IF(Table1[[#This Row],[customer_subscription]]=1,"Subscribed","Not Subscribed") -> Subscribed
A13: 12 | B13: 30 | C13: Male | D13: 12 | E13: Shorts | F13: Clothing | G13: 12 | H13: 213 | I13: 68 | J13: Hawaii | K13: S | L13: Olive | M13: Winter | N13: 4.9 | O13: 1 | P13: Store Pickup | Q13: Yes | R13: Yes | S13: 10 | T13: Bank Transfer | U13: Fortnightly | V13: 45311 | W13: =Table1[[#This Row],[customer_purchase count]]+1 -> 11 | X13: =Table1[[#This Row],[customer_purchase count]]*Rules!$B$3 -> 597.64359 | Y13: =IF(Table1[[#This Row],[customer_subscription]]=1,"Subscribed","Not Subscribed") -> Subscribed
... A18: 17 | B18: 25 | C18: Male | D18: 17 | E18: Sunglasses | F18: Accessories | G18: 17 | H18: 219 | I18: 36 | J18: Alabama | K18: S | L18: Gray | M18: Spring | N18: 4.1 | O18: 1 | P18: Next Day Air | Q18: Yes | R18: Yes | S18: 44 | T18: Debit Card | U18: Bi-Weekly | V18: 45430 | W18: =Table1[[#This Row],[customer_purchase count]]+1 -> 45 | X18: =Table1[[#This Row],[customer_purchase count]]*Rules!$B$3 -> 2629.6318 | Y18: =IF(Table1[[#This Row],[customer_subscription]]=1,"Subscribed","Not Subscribed") -> Subscribed
A19: 18 | B19: 53 | C19: Male | D19: 18 | E19: Dress | F19: Clothing | G19: 18 | H19: 220 | I19: 38 | J19: Mississippi | K19: XL | L19: Lavender | M19: Winter | N19: 4.7 | O19: 1 | P19: 2-Day Shipping | Q19: Yes | R19: Yes | S19: 36 | T19: Venmo | U19: Quarterly | V19: 45346 | W19: =Table1[[#This Row],[customer_purchase count]]+1 -> 37 | X19: =Table1[[#This Row],[customer_purchase count]]*Rules!$B$3 -> 2151.5169 | Y19: =IF(Table1[[#This Row],[customer_subscription]]=1,"Subscribed","Not Subscribed") -> Subscribed | Z19: Loyal High Spenders
A20: 19 | B20: 52 | C20: Male | D20: 19 | E20: Sweater | F20: Clothing | G20: 19 | H20: 221 | I20: 48 | J20: Montana | K20: S | L20: Black | M20: Summer | N20: 4.6 | O20: 1 | P20: Free Shipping | Q20: Yes | R20: Yes | S20: 17 | T20: Cash | U20: Weekly | V20: 45466 | W20: =Table1[[#This Row],[customer_purchase count]]+1 -> 18 | X20: =Table1[[#This Row],[customer_purchase count]]*Rules!$B$3 -> 1015.9941 | Y20: =IF(Table1[[#This Row],[customer_subscription]]=1,"Subscribed","Not Subscribed") -> Subscribed
A21: 20 | B21: 66 | C21: Male | D21: 20 | E21: Pants | F21: Clothing | G21: 20 | H21: 223 | I21: 90 | J21: Rhode Island | K21: M | L21: Green | M21: Summer | N21: 3.3 | O21: 1 | P21: Standard | Q21: Yes | R21: Yes | S21: 46 | T21: Debit Card | U21: Bi-Weekly | V21: 45452 | W21: =Table1[[#This Row],[customer_purchase count]]+1 -> 47 | X21: =Table1[[#This Row],[customer_purchase count]]*Rules!$B$3 -> 2749.1605 | Y21: =IF(Table1[[#This Row],[customer_subscription]]=1,"Subscribed","Not Subscribed") -> Subscribed
A22: 21 | B22: 21 | C22: Male | D22: 21 | E22: Pants | F22: Clothing | G22: 21 | H22: 224 | I22: 51 | J22: Louisiana | K22: M | L22: Black | M22: Winter | N22: 2.8 | O22: 1 | P22: Express | Q22: Yes | R22: Yes | S22: 50 | T22: Cash | U22: Every 3 Months | V22: 45641 | W22: =Table1[[#This Row],[customer_purchase count]]+1 -> 51 | X22: =Table1[[#This Row],[customer_purchase count]]*Rules!$B$3 -> 2988.2179 | Y22: =IF(Table1[[#This Row],[customer_subscription]]=1,"Subscribed","Not Subscribed") -> Subscribed
A23: 22 | B23: 31 | C23: Male | D23: 22 | E23: Pants | F23: Clothing | G23: 22 | H23: 225 | I23: 62 | J23: North Carolina | K23: M | L23: Charcoal | M23: Winter | N23: 4.1 | O23: 1 | P23: Store Pickup | Q23: Yes | R23: Yes | S23: 22 | T23: Debit Card | U23: Quarterly | V23: 45308 | W23: =Table1[[#This Row],[customer_purchase count]]+1 -> 23 | X23: =Table1[[#This Row],[customer_purchase count]]*Rules!$B$3 -> 1314.8159 | Y23: =IF(Table1[[#This Row],[customer_subscription]]=1,"Subscribed","Not Subscribed") -> Subscribed
A24: 23 | B24: 56 | C24: Male | D24: 23 | E24: Pants | F24: Clothing | G24: 23 | H24: 226 | I24: 37 | J24: California | K24: M | L24: Peach | M24: Summer | N24: 3.2 | O24: 1 | P24: Store Pickup | Q24: Yes | R24: Yes | S24: 32 | T24: Debit Card | U24: Annually | V24: 45527 | W24: =Table1[[#This Row],[customer_purchase count]]+1 -> 33 | X24: =Table1[[#This Row],[customer_purchase count]]*Rules!$B$3 -> 1912.4595 | Y24: =IF(Table1[[#This Row],[customer_subscription]]=1,"Subscribed","Not Subscribed") -> Subscribed
A25: 24 | B25: 31 | C25: Male | D25: 24 | E25: Pants | F25: Clothing | G25: 24 | H25: 227 | I25: 88 | J25: Oklahoma | K25: XL | L25: White | M25: Winter | N25: 4.4 | O25: 1 | P25: Express | Q25: Yes | R25: Yes | S25: 40 | T25: Credit Card | U25: Weekly | V25: 45627 | W25: =Table1[[#This Row],[customer_purchase count]]+1 -> 41 | X25: =Table1[[#This Row],[customer_purchase count]]*Rules!$B$3 -> 2390.5744 | Y25: =IF(Table1[[#This Row],[customer_subscription]]=1,"Subscribed","Not Subscribed") -> Subscribed | Z25: Loyal High Spenders
A26: 25 | B26: 18 | C26: Male | D26: 25 | E26: Jacket | F26: Outerwear | G26: 25 | H26: 229 | I26: 22 | J26: Florida | K26: M | L26: Green | M26: Fall | N26: 2.9 | O26: 1 | P26: Store Pickup | Q26: Yes | R26: Yes | S26: 16 | T26: Debit Card | U26: Weekly | V26: 45579 | W26: =Table1[[#This Row],[customer_purchase count]]+1 -> 17 | X26: =Table1[[#This Row],[customer_purchase count]]*Rules!$B$3 -> 956.22974 | Y26: =IF(Table1[[#This Row],[customer_subscription]]=1,"Subscribed","Not Subscribed") -> Subscribed | Z26: Young Budget Shoppers
A27: 26 | B27: 18 | C27: Male | D27: 26 | E27: Hoodie | F27: Clothing | G27: 26 | H27: 230 | I27: 25 | J27: Texas | K27: M | L27: Silver | M27: Summer | N27: 3.6 | O27: 1 | P27: Express | Q27: Yes | R27: Yes | S27: 14 | T27: PayPal | U27: Annually | V27: 45465 | W27: =Table1[[#This Row],[customer_purchase count]]+1 -> 15 | X27: =Table1[[#This Row],[customer_purchase count]]*Rules!$B$3 -> 836.70103 | Y27: =IF(Table1[[#This Row],[customer_subscription]]=1,"Subscribed","Not Subscribed") -> Subscribed | Z27: Young Budget Shoppers
A28: 27 | B28: 38 | C28: Male | D28: 27 | E28: Jewelry | F28: Accessories | G28: 27 | H28: 231 | I28: 20 | J28: Nevada | K28: M | L28: Red | M28: Spring | N28: 3.6 | O28: 1 | P28: Next Day Air | Q28: Yes | R28: Yes | S28: 13 | T28: Credit Card | U28: Annually | V28: 45388 | W28: =Table1[[#This Row],[customer_purchase count]]+1 -> 14 | X28: =Table1[[#This Row],[customer_purchase count]]*Rules!$B$3 -> 776.93667 | Y28: =IF(Table1[[#This Row],[customer_subscription]]=1,"Subscribed","Not Subscribed") -> Subscribed
A29: 28 | B29: 56 | C29: Male | D29: 28 | E29: Shorts | F29: Clothing | G29: 28 | H29: 232 | I29: 56 | J29: Kentucky | K29: L | L29: Cyan | M29: Summer | N29: 5 | O29: 1 | P29: Next Day Air | Q29: Yes | R29: Yes | S29: 7 | T29: Bank Transfer | U29: Every 3 Months | V29: 45521 | W29: =Table1[[#This Row],[customer_purchase count]]+1 -> 8 | X29: =Table1[[#This Row],[customer_purchase count]]*Rules!$B$3 -> 418.35051 | Y29: =IF(Table1[[#This Row],[customer_subscription]]=1,"Subscribed","Not Subscribed") -> Subscribed
A30: 29 | B30: 54 | C30: Male | D30: 29 | E30: Handbag | F30: Accessories | G30: 29 | H30: 233 | I30: 94 | J30: North Carolina | K30: M | L30: Gray | M30: Fall | N30: 4.4 | O30: 1 | P30: Free Shipping | Q30: Yes | R30: Yes | S30: 41 | T30: PayPal | U30: Every 3 Months | V30: 45609 | W30: =Table1[[#This Row],[customer_purchase count]]+1 -> 42 | X30: =Table1[[#This Row],[customer_purchase count]]*Rules!$B$3 -> 2450.3387 | Y30: =IF(Table1[[#This Row],[customer_subscription]]=1,"Subscribed","Not Subscribed") -> Subscribed | Z30: Loyal High Spenders
A31: 30 | B31: 31 | C31: Male | D31: 30 | E31: Dress | F31: Clothing | G31: 30 | H31: 235 | I31: 48 | J31: Wyoming | K31: S | L31: Black | M31: Fall | N31: 4.1 | O31: 1 | P31: Store Pickup | Q31: Yes | R31: Yes | S31: 14 | T31: Credit Card | U31: Weekly | V31: 45544 | W31: =Table1[[#This Row],[customer_purchase count]]+1 -> 15 | X31: =Table1[[#This Row],[customer_purchase count]]*Rules!$B$3 -> 836.70103 | Y31: =IF(Table1[[#This Row],[customer_subscription]]=1,"Subscribed","Not Subscribed") -> Subscribed
A32: 31 | B32: 57 | C32: Male | D32: 31 | E32: Jewelry | F32: Accessories | G32: 31 | H32: 236 | I32: 31 | J32: North Carolina | K32: L | L32: Black | M32: Winter | N32: 4.7 | O32: 1 | P32: Standard | Q32: Yes | R32: Yes | S32: 16 | T32: Credit Card | U32: Monthly | V32: 45299 | W32: =Table1[[#This Row],[customer_purchase count]]+1 -> 17 | X32: =Table1[[#This Row],[customer_purchase count]]*Rules!$B$3 -> 956.22974 | Y32: =IF(Table1[[#This Row],[customer_subscription]]=1,"Subscribed","Not Subscribed") -> Subscribed
A33: 32 | B33: 33 | C33: Male | D33: 32 | E33: Dress | F33: Clothing | G33: 32 | H33: 237 | I33: 79 | J33: West Virginia | K33: L | L33: Brown | M33: Winter | N33: 4.7 | O33: 1 | P33: Store Pickup | Q33: Yes | R33: Yes | S33: 45 | T33: Venmo | U33: Monthly | V33: 45314 | W33: =Table1[[#This Row],[customer_purchase count]]+1 -> 46 | X33: =Table1[[#This Row],[customer_purchase count]]*Rules!$B$3 -> 2689.3962 | Y33: =IF(Table1[[#This Row],[customer_subscription]]=1,"Subscribed","Not Subscribed") -> Subscribed | Z33: Loyal High Spenders
A34: 33 | B34: 36 | C34: Male | D34: 33 | E34: Jacket | F34: Outerwear | G34: 33 | H34: 238 | I34: 67 | J34: Kansas | K34: M | L34: Silver | M34: Summer | N34: 4.9 | O34: 1 | P34: Free Shipping | Q34: Yes | R34: Yes | S34: 37 | T34: Venmo | U34: Annually | V34: 45454 | W34: =Table1[[#This Row],[customer_purchase count]]+1 -> 38 | X34: =Table1[[#This Row],[customer_purchase count]]*Rules!$B$3 -> 2211.2813 | Y34: =IF(Table1[[#This Row],[customer_subscription]]=1,"Subscribed","Not Subscribed") -> Subscribed | Z34: Loyal High Spenders
A35: 34 | B35: 54 | C35: Male | D35: 34 | E35: Pants | F35: Clothing | G35: 34 | H35: 239 | I35: 38 | J35: Colorado | K35: L | L35: Green | M35: Summer | N35: 3.3 | O35: 1 | P35: Store Pickup | Q35: Yes | R35: Yes | S35: 45 | T35: Cash | U35: Quarterly | V35: 45474 | W35: =Table1[[#This Row],[customer_purchase count]]+1 -> 46 | X35: =Table1[[#This Row],[customer_purchase count]]*Rules!$B$3 -> 2689.3962 | Y35: =IF(Table1[[#This Row],[customer_subscription]]=1,"Subscribed","Not Subscribed") -> Subscribed | Z35: Loyal High Spenders
A36: 35 | B36: 36 | C36: Male | D36: 35 | E36: T-shirt | F36: Clothing | G36: 35 | H36: 241 | I36: 91 | J36: North Dakota | K36: L | L36: Violet | M36: Spring | N36: 4.6 | O36: 1 | P36: 2-Day Shipping | Q36: Yes | R36: Yes | S36: 38 | T36: PayPal | U36: Quarterly | V36: 45423 | W36: =Table1[[#This Row],[customer_purchase count]]+1 -> 39 | X36: =Table1[[#This Row],[customer_purchase count]]*Rules!$B$3 -> 2271.0456 | Y36: =IF(Table1[[#This Row],[customer_subscription]]=1,"Subscribed","Not Subscribed") -> Subscribed | Z36: Loyal High Spenders
A37: 36 | B37: 54 | C37: Male | D37: 36 | E37: Blouse | F37: Clothing | G37: 36 | H37: 242 | I37: 33 | J37: Massachusetts | K37: M | L37: Cyan | M37: Summer | N37: 4 | O37: 1 | P37: 2-Day Shipping | Q37: Yes | R37: Yes | S37: 48 | T37: Credit Card | U37: Bi-Weekly | V37: 45463 | W37: =Table1[[#This Row],[customer_purchase count]]+1 -> 49 | X37: =Table1[[#This Row],[customer_purchase count]]*Rules!$B$3 -> 2868.6892 | Y37: =IF(Table1[[#This Row],[customer_subscription]]=1,"Subscribed","Not Subscribed") -> Subscribed | Z37: Loyal High Spenders
A38: 37 | B38: 35 | C38: Male | D38: 37 | E38: T-shirt | F38: Clothing | G38: 37 | H38: 243 | I38: 69 | J38: Illinois | K38: M | L38: Maroon | M38: Winter | N38: 4.6 | O38: 1 | P38: Free Shipping | Q38: Yes | R38: Yes | S38: 44 | T38: PayPal | U38: Fortnightly | V38: 45631 | W38: =Table1[[#This Row],[customer_purchase count]]+1 -> 45 | X38: =Table1[[#This Row],[customer_purchase count]]*Rules!$B$3 -> 2629.6318 | Y38: =IF(Table1[[#This Row],[customer_subscription]]=1,"Subscribed","Not Subscribed") -> Subscribed | Z38: Loyal High Spenders
A39: 38 | B39: 35 | C39: Male | D39: 38 | E39: Jeans | F39: Clothing | G39: 38 | H39: 244 | I39: 45 | J39: Indiana | K39: S | L39: Cyan | M39: Summer | N39: 2.8 | O39: 1 | P39: Store Pickup | Q39: Yes | R39: Yes | S39: 10 | T39: PayPal | U39: Weekly | V39: 45519 | W39: =Table1[[#This Row],[customer_purchase count]]+1 -> 11 | X39: =Table1[[#This Row],[customer_purchase count]]*Rules!$B$3 -> 597.64359 | Y39: =IF(Table1[[#This Row],[customer_subscription]]=1,"Subscribed","Not Subscribed") -> Subscribed
A40: 39 | B40: 29 | C40: Male | D40: 39 | E40: Dress | F40: Clothing | G40: 39 | H40: 245 | I40: 37 | J40: Florida | K40: M | L40: Red | M40: Winter | N40: 3.7 | O40: 1 | P40: 2-Day Shipping | Q40: Yes | R40: Yes | S40: 44 | T40: Venmo | U40: Every 3 Months | V40: 45332 | W40: =Table1[[#This Row],[customer_purchase count]]+1 -> 45 | X40: =Table1[[#This Row],[customer_purchase count]]*Rules!$B$3 -> 2629.6318 | Y40: =IF(Table1[[#This Row],[customer_subscription]]=1,"Subscribed","Not Subscribed") -> Subscribed
A41: 40 | B41: 70 | C41: Male | D41: 40 | E41: Pants | F41: Clothing | G41: 40 | H41: 247 | I41: 60 | J41: Arizona | K41: S | L41: Turquoise | M41: Summer | N41: 4.2 | O41: 1 | P41: Express | Q41: Yes | R41: Yes | S41: 18 | T41: Credit Card | U41: Monthly | V41: 45497 | W41: =Table1[[#This Row],[customer_purchase count]]+1 -> 19 | X41: =Table1[[#This Row],[customer_purchase count]]*Rules!$B$3 -> 1075.7585 | Y41: =IF(Table1[[#This Row],[customer_subscription]]=1,"Subscribed","Not Subscribed") -> Subscribed
A42: 41 | B42: 69 | C42: Male | D42: 41 | E42: Handbag | F42: Accessories | G42: 41 | H42: 248 | I42: 76 | J42: Louisiana | K42: L | L42: Beige | M42: Winter | N42: 4.6 | O42: 1 | P42: Next Day Air | Q42: Yes | R42: Yes | S42: 31 | T42: Debit Card | U42: Quarterly | V42: 45345 | W42: =Table1[[#This Row],[customer_purchase count]]+1 -> 32 | X42: =Table1[[#This Row],[customer_purchase count]]*Rules!$B$3 -> 1852.6951 | Y42: =IF(Table1[[#This Row],[customer_subscription]]=1,"Subscribed","Not Subscribed") -> Subscribed
A43: 42 | B43: 67 | C43: Male | D43: 42 | E43: Scarf | F43: Accessories | G43: 42 | H43: 249 | I43: 39 | J43: Alaska | K43: M | L43: Orange | M43: Spring | N43: 4.5 | O43: 1 | P43: Standard | Q43: Yes | R43: Yes | S43: 40 | T43: Venmo | U43: Annually | V43: 45371 | W43: =Table1[[#This Row],[customer_purchase count]]+1 -> 41 | X43: =Table1[[#This Row],[customer_purchase count]]*Rules!$B$3 -> 2390.5744 | Y43: =IF(Table1[[#This Row],[customer_subscription]]=1,"Subscribed","Not Subscribed") -> Subscribed
A44: 43 | B44: 20 | C44: Male | D44: 43 | E44: Coat | F44: Outerwear | G44: 43 | H44: 250 | I44: 100 | J44: Tennessee | K44: M | L44: Beige | M44: Spring | N44: 4.1 | O44: 1 | P44: Free Shipping | Q44: Yes | R44: Yes | S44: 15 | T44: PayPal | U44: Annually | V44: 45427 | W44: =Table1[[#This Row],[customer_purchase count]]+1 -> 16 | X44: =Table1[[#This Row],[customer_purchase count]]*Rules!$B$3 -> 896.46538 | Y44: =IF(Table1[[#This Row],[customer_subscription]]=1,"Subscribed","Not Subscribed") -> Subscribed | Z44: Young Budget Shoppers
A45: 44 | B45: 25 | C45: Male | D45: 44 | E45: Scarf | F45: Accessories | G45: 44 | H45: 251 | I45: 69 | J45: Ohio | K45: L | L45: Lavender | M45: Fall | N45: 3.7 | O45: 1 | P45: Store Pickup | Q45: Yes | R45: Yes | S45: 19 | T45: PayPal | U45: Fortnightly | V45: 45558 | W45: =Table1[[#This Row],[customer_purchase count]]+1 -> 20 | X45: =Table1[[#This Row],[customer_purchase count]]*Rules!$B$3 -> 1135.5228 | Y45: =IF(Table1[[#This Row],[customer_subscription]]=1,"Subscribed","Not Subscribed") -> Subscribed
A46: 45 | B46: 39 | C46: Male | D46: 45 | E46: Hat | F46: Accessories | G46: 45 | H46: 253 | I46: 53 | J46: Kentucky | K46: S | L46: Silver | M46: Summer | N46: 4.6 | O46: 1 | P46: Free Shipping | Q46: Yes | R46: Yes | S46: 45 | T46: PayPal | U46: Weekly | V46: 45469 | W46: =Table1[[#This Row],[customer_purchase count]]+1 -> 46 | X46: =Table1[[#This Row],[customer_purchase count]]*Rules!$B$3 -> 2689.3962 | Y46: =IF(Table1[[#This Row],[customer_subscription]]=1,"Subscribed","Not Subscribed") -> Subscribed | Z46: Loyal High Spenders
A47: 46 | B47: 50 | C47: Male | D47: 46 | E47: Socks | F47: Clothing | G47: 46 | H47: 254 | I47: 21 | J47: Tennessee | K47: XL | L47: Indigo | M47: Fall | N47: 2.9 | O47: 1 | P47: 2-Day Shipping | Q47: Yes | R47: Yes | S47: 25 | T47: PayPal | U47: Annually | V47: 45549 | W47: =Table1[[#This Row],[customer_purchase count]]+1 -> 26 | X47: =Table1[[#This Row],[customer_purchase count]]*Rules!$B$3 -> 1494.109 | Y47: =IF(Table1[[#This Row],[customer_subscription]]=1,"Subscribed","Not Subscribed") -> Subscribed
A48: 47 | B48: 57 | C48: Male | D48: 47 | E48: Shirt | F48: Clothing | G48: 47 | H48: 255 | I48: 43 | J48: California | K48: L | L48: White | M48: Summer | N48: 2.9 | O48: 1 | P48: Store Pickup | Q48: Yes | R48: Yes | S48: 45 | T48: Cash | U48: Quarterly | V48: 45501 | W48: =Table1[[#This Row],[customer_purchase count]]+1 -> 46 | X48: =Table1[[#This Row],[customer_purchase count]]*Rules!$B$3 -> 2689.3962 | Y48: =IF(Table1[[#This Row],[customer_subscription]]=1,"Subscribed","Not Subscribed") -> Subscribed | Z48: Loyal High Spenders
A49: 48 | B49: 55 | C49: Male | D49: 48 | E49: Jewelry | F49: Accessories | G49: 48 | H49: 256 | I49: 54 | J49: Montana | K49: M | L49: Charcoal | M49: Winter | N49: 4.5 | O49: 1 | P49: Free Shipping | Q49: Yes | R49: Yes | S49: 36 | T49: Cash | U49: Weekly | V49: 45632 | W49: =Table1[[#This Row],[customer_purchase count]]+1 -> 37 | X49: =Table1[[#This Row],[customer_purchase count]]*Rules!$B$3 -> 2151.5169 | Y49: =IF(Table1[[#This Row],[customer_subscription]]=1,"Subscribed","Not Subscribed") -> Subscribed | Z49: Loyal High Spenders
A50: 49 | B50: 42 | C50: Male | D50: 49 | E50: Shirt | F50: Clothing | G50: 49 | H50: 257 | I50: 55 | J50: Nevada | K50: M | L50: Orange | M50: Summer | N50: 2.7 | O50: 1 | P50: Store Pickup | Q50: Yes | R50: Yes | S50: 38 | T50: Cash | U50: Monthly | V50: 45467 | W50: =Table1[[#This Row],[customer_purchase count]]+1 -> 39 | X50: =Table1[[#This Row],[customer_purchase count]]*Rules!$B$3 -> 2271.0456 | Y50: =IF(Table1[[#This Row],[customer_subscription]]=1,"Subscribed","Not Subscribed") -> Subscribed | Z50: Loyal High Spenders
A51: 50 | B51: 68 | C51: Male | D51: 50 | E51: Hoodie | F51: Clothing | G51: 50 | H51: 259 | I51: 30 | J51: New Jersey | K51: S | L51: Indigo | M51: Spring | N51: 4.6 | O51: 1 | P51: Next Day Air | Q51: Yes | R51: Yes | S51: 34 | T51: Debit Card | U51: Bi-Weekly | V51: 45370 | W51: =Table1[[#This Row],[customer_purchase count]]+1 -> 35 | X51: =Table1[[#This Row],[customer_purchase count]]*Rules!$B$3 -> 2031.9882 | Y51: =IF(Table1[[#This Row],[customer_subscription]]=1,"Subscribed","Not Subscribed") -> Subscribed
A52: 51 | B52: 49 | C52: Male | D52: 51 | E52: Blouse | F52: Clothing | G52: 51 | H52: 260 | I52: 28 | J52: Maryland | K52: M | L52: Red | M52: Spring | N52: 3.7 | O52: 1 | P52: Store Pickup | Q52: Yes | R52: Yes | S52: 39 | T52: Debit Card | U52: Bi-Weekly | V52: 45367 | W52: =Table1[[#This Row],[customer_purchase count]]+1 -> 40 | X52: =Table1[[#This Row],[customer_purchase count]]*Rules!$B$3 -> 2330.81 | Y52: =IF(Table1[[#This Row],[customer_subscription]]=1,"Subscribed","Not Subscribed") -> Subscribed | Z52: Loyal High Spenders
A53: 52 | B53: 59 | C53: Male | D53: 52 | E53: Skirt | F53: Clothing | G53: 52 | H53: 261 | I53: 59 | J53: Vermont | K53: XL | L53: Gray | M53: Winter | N53: 4.7 | O53: 1 | P53: 2-Day Shipping | Q53: Yes | R53: Yes | S53: 7 | T53: Credit Card | U53: Quarterly | V53: 45339 | W53: =Table1[[#This Row],[customer_purchase count]]+1 -> 8 | X53: =Table1[[#This Row],[customer_purchase count]]*Rules!$B$3 -> 418.35051 | Y53: =IF(Table1[[#This Row],[customer_subscription]]=1,"Subscribed","Not Subscribed") -> Subscribed
A54: 53 | B54: 42 | C54: Male | D54: 53 | E54: T-shirt | F54: Clothing | G54: 53 | H54: 262 | I54: 20 | J54: Alaska | K54: M | L54: Green | M54: Summer | N54: 2.6 | O54: 1 | P54: Free Shipping | Q54: Yes | R54: Yes | S54: 26 | T54: Credit Card | U54: Weekly | V54: 45450 | W54: =Table1[[#This Row],[customer_purchase count]]+1 -> 27 | X54: =Table1[[#This Row],[customer_purchase count]]*Rules!$B$3 -> 1553.8733 | Y54: =IF(Table1[[#This Row],[customer_subscription]]=1,"Subscribed","Not Subscribed") -> Subscribed
A55: 54 | B55: 29 | C55: Male | D55: 54 | E55: Skirt | F55: Clothing | G55: 54 | H55: 263 | I55: 24 | J55: Mississippi | K55: S | L55: Peach | M55: Winter | N55: 3.9 | O55: 1 | P55: Next Day Air | Q55: Yes | R55: Yes | S55: 35 | T55: Credit Card | U55: Weekly | V55: 45312 | W55: =Table1[[#This Row],[customer_purchase count]]+1 -> 36 | X55: =Table1[[#This Row],[customer_purchase count]]*Rules!$B$3 -> 2091.7526 | Y55: =IF(Table1[[#This Row],[customer_subscription]]=1,"Subscribed","Not Subscribed") -> Subscribed
A56: 55 | B56: 47 | C56: Male | D56: 55 | E56: Coat | F56: Outerwear | G56: 55 | H56: 265 | I56: 94 | J56: New Mexico | K56: M | L56: Brown | M56: Summer | N56: 4.2 | O56: 1 | P56: Next Day Air | Q56: Yes | R56: Yes | S56: 35 | T56: Debit Card | U56: Bi-Weekly | V56: 45495 | W56: =Table1[[#This Row],[customer_purchase count]]+1 -> 36 | X56: =Table1[[#This Row],[customer_purchase count]]*Rules!$B$3 -> 2091.7526 | Y56: =IF(Table1[[#This Row],[customer_subscription]]=1,"Subscribed","Not Subscribed") -> Subscribed | Z56: Loyal High Spenders
A57: 56 | B57: 40 | C57: Male | D57: 56 | E57: Jacket | F57: Outerwear | G57: 56 | H57: 266 | I57: 28 | J57: South Carolina | K57: M | L57: Lavender | M57: Winter | N57: 3 | O57: 1 | P57: 2-Day Shipping | Q57: Yes | R57: Yes | S57: 49 | T57: Credit Card | U57: Annually | V57: 45344 | W57: =Table1[[#This Row],[customer_purchase count]]+1 -> 50 | X57: =Table1[[#This Row],[customer_purchase count]]*Rules!$B$3 -> 2928.4536 | Y57: =IF(Table1[[#This Row],[customer_subscription]]=1,"Subscribed","Not Subscribed") -> Subscribed | Z57: Loyal High Spenders
A58: 57 | B58: 41 | C58: Male | D58: 57 | E58: Backpack | F58: Accessories | G58: 57 | H58: 267 | I58: 73 | J58: Mississippi | K58: XL | L58: Brown | M58: Summer | N58: 4.7 | O58: 1 | P58: Store Pickup | Q58: Yes | R58: Yes | S58: 46 | T58: Credit Card | U58: Weekly | V58: 45450 | W58: =Table1[[#This Row],[customer_purchase count]]+1 -> 47 | X58: =Table1[[#This Row],[customer_purchase count]]*Rules!$B$3 -> 2749.1605 | Y58: =IF(Table1[[#This Row],[customer_subscription]]=1,"Subscribed","Not Subscribed") -> Subscribed | Z58: Loyal High Spenders
A59: 58 | B59: 21 | C59: Male | D59: 58 | E59: Coat | F59: Outerwear | G59: 58 | H59: 268 | I59: 64 | J59: West Virginia | K59: M | L59: White | M59: Summer | N59: 4.4 | O59: 1 | P59: Store Pickup | Q59: Yes | R59: Yes | S59: 17 | T59: Debit Card | U59: Fortnightly | V59: 45493 | W59: =Table1[[#This Row],[customer_purchase count]]+1 -> 18 | X59: =Table1[[#This Row],[customer_purchase count]]*Rules!$B$3 -> 1015.9941 | Y59: =IF(Table1[[#This Row],[customer_subscription]]=1,"Subscribed","Not Subscribed") -> Subscribed | Z59: Young Budget Shoppers
A60: 59 | B60: 69 | C60: Male | D60: 59 | E60: Hoodie | F60: Clothing | G60: 59 | H60: 269 | I60: 54 | J60: Missouri | K60: M | L60: Charcoal | M60: Summer | N60: 4.2 | O60: 1 | P60: Free Shipping | Q60: Yes | R60: Yes | S60: 29 | T60: Venmo | U60: Monthly | V60: 45514 | W60: =Table1[[#This Row],[customer_purchase count]]+1 -> 30 | X60: =Table1[[#This Row],[customer_purchase count]]*Rules!$B$3 -> 1733.1664 | Y60: =IF(Table1[[#This Row],[customer_subscription]]=1,"Subscribed","Not Subscribed") -> Subscribed
A61: 60 | B61: 63 | C61: Male | D61: 60 | E61: Belt | F61: Accessories | G61: 60 | H61: 271 | I61: 79 | J61: Louisiana | K61: L | L61: Yellow | M61: Spring | N61: 4.6 | O61: 1 | P61: Standard | Q61: Yes | R61: Yes | S61: 4 | T61: Debit Card | U61: Weekly | V61: 45440 | W61: =Table1[[#This Row],[customer_purchase count]]+1 -> 5 | X61: =Table1[[#This Row],[customer_purchase count]]*Rules!$B$3 -> 239.05744 | Y61: =IF(Table1[[#This Row],[customer_subscription]]=1,"Subscribed","Not Subscribed") -> Subscribed
A62: 61 | B62: 50 | C62: Male | D62: 61 | E62: Sweater | F62: Clothing | G62: 61 | H62: 272 | I62: 37 | J62: Idaho | K62: L | L62: Brown | M62: Summer | N62: 4 | O62: 1 | P62: Express | Q62: Yes | R62: Yes | S62: 17 | T62: Cash | U62: Weekly | V62: 45501 | W62: =Table1[[#This Row],[customer_purchase count]]+1 -> 18 | X62: =Table1[[#This Row],[customer_purchase count]]*Rules!$B$3 -> 1015.9941 | Y62: =IF(Table1[[#This Row],[customer_subscription]]=1,"Subscribed","Not Subscribed") -> Subscribed
A63: 62 | B63: 55 | C63: Male | D63: 62 | E63: Scarf | F63: Accessories | G63: 62 | H63: 273 | I63: 68 | J63: Texas | K63: M | L63: Orange | M63: Winter | N63: 4.7 | O63: 1 | P63: Store Pickup | Q63: Yes | R63: Yes | S63: 21 | T63: Credit Card | U63: Every 3 Months | V63: 45348 | W63: =Table1[[#This Row],[customer_purchase count]]+1 -> 22 | X63: =Table1[[#This Row],[customer_purchase count]]*Rules!$B$3 -> 1255.0515 | Y63: =IF(Table1[[#This Row],[customer_subscription]]=1,"Subscribed","Not Subscribed") -> Subscribed
A64: 63 | B64: 30 | C64: Male | D64: 63 | E64: Sneakers | F64: Footwear | G64: 63 | H64: 274 | I64: 21 | J64: Mississippi | K64: S | L64: Magenta | M64: Spring | N64: 3.8 | O64: 1 | P64: Free Shipping | Q64: Yes | R64: Yes | S64: 31 | T64: Credit Card | U64: Fortnightly | V64: 45425 | W64: =Table1[[#This Row],[customer_purchase count]]+1 -> 32 | X64: =Table1[[#This Row],[customer_purchase count]]*Rules!$B$3 -> 1852.6951 | Y64: =IF(Table1[[#This Row],[customer_subscription]]=1,"Subscribed","Not Subscribed") -> Subscribed
A65: 64 | B65: 33 | C65: Male | D65: 64 | E65: Sunglasses | F65: Accessories | G65: 64 | H65: 275 | I65: 79 | J65: Arizona | K65: L | L65: Lavender | M65: Winter | N65: 2.7 | O65: 1 | P65: 2-Day Shipping | Q65: Yes | R65: Yes | S65: 43 | T65: Credit Card | U65: Weekly | V65: 45299 | W65: =Table1[[#This Row],[customer_purchase count]]+1 -> 44 | X65: =Table1[[#This Row],[customer_purchase count]]*Rules!$B$3 -> 2569.8674 | Y65: =IF(Table1[[#This Row],[customer_subscription]]=1,"Subscribed","Not Subscribed") -> Subscribed | Z65: Loyal High Spenders
A66: 65 | B66: 65 | C66: Male | D66: 65 | E66: Boots | F66: Footwear | G66: 65 | H66: 277 | I66: 83 | J66: Alabama | K66: S | L66: Green | M66: Fall | N66: 4.8 | O66: 1 | P66: Standard | Q66: Yes | R66: Yes | S66: 18 | T66: Debit Card | U66: Fortnightly | V66: 45597 | W66: =Table1[[#This Row],[customer_purchase count]]+1 -> 19 | X66: =Table1[[#This Row],[customer_purchase count]]*Rules!$B$3 -> 1075.7585 | Y66: =IF(Table1[[#This Row],[customer_subscription]]=1,"Subscribed","Not Subscribed") -> Subscribed
A67: 66 | B67: 65 | C67: Male | D67: 66 | E67: Backpack | F67: Accessories | G67: 66 | H67: 278 | I67: 36 | J67: New Jersey | K67: M | L67: Purple | M67: Spring | N67: 4.8 | O67: 1 | P67: 2-Day Shipping | Q67: Yes | R67: Yes | S67: 44 | T67: Venmo | U67: Every 3 Months | V67: 45433 | W67: =Table1[[#This Row],[customer_purchase count]]+1 -> 45 | X67: =Table1[[#This Row],[customer_purchase count]]*Rules!$B$3 -> 2629.6318 | Y67: =IF(Table1[[#This Row],[customer_subscription]]=1,"Subscribed","Not Subscribed") -> Subscribed
A68: 67 | B68: 31 | C68: Male | D68: 67 | E68: Blouse | F68: Clothing | G68: 67 | H68: 279 | I68: 94 | J68: Pennsylvania | K68: S | L68: Magenta | M68: Winter | N68: 4.7 | O68: 1 | P68: 2-Day Shipping | Q68: Yes | R68: Yes | S68: 3 | T68: Venmo | U68: Every 3 Months | V68: 45308 | W68: =Table1[[#This Row],[customer_purchase count]]+1 -> 4 | X68: =Table1[[#This Row],[customer_purchase count]]*Rules!$B$3 -> 179.29308 | Y68: =IF(Table1[[#This Row],[customer_subscription]]=1,"Subscribed","Not Subscribed") -> Subscribed
A69: 68 | B69: 45 | C69: Male | D69: 68 | E69: Coat | F69: Outerwear | G69: 68 | H69: 280 | I69: 33 | J69: Connecticut | K69: L | L69: Gray | M69: Winter | N69: 4.4 | O69: 1 | P69: Store Pickup | Q69: Yes | R69: Yes | S69: 49 | T69: Debit Card | U69: Monthly | V69: 45350 | W69: =Table1[[#This Row],[customer_purchase count]]+1 -> 50 | X69: =Table1[[#This Row],[customer_purchase count]]*Rules!$B$3 -> 2928.4536 | Y69: =IF(Table1[[#This Row],[customer_subscription]]=1,"Subscribed","Not Subscribed") -> Subscribed | Z69: Loyal High Spenders
A70: 69 | B70: 57 | C70: Male | D70: 69 | E70: Handbag | F70: Accessories | G70: 69 | H70: 281 | I70: 46 | J70: Utah | K70: L | L70: Silver | M70: Summer | N70: 3.9 | O70: 1 | P70: Next Day Air | Q70: Yes | R70: Yes | S70: 21 | T70: Cash | U70: Every 3 Months | V70: 45515 | W70: =Table1[[#This Row],[customer_purchase count]]+1 -> 22 | X70: =Table1[[#This Row],[customer_purchase count]]*Rules!$B$3 -> 1255.0515 | Y70: =IF(Table1[[#This Row],[customer_subscription]]=1,"Subscribed","Not Subscribed") -> Subscribed
A71: 70 | B71: 48 | C71: Male | D71: 70 | E71: Belt | F71: Accessories | G71: 70 | H71: 283 | I71: 70 | J71: Tennessee | K71: S | L71: Cyan | M71: Summer | N71: 4.4 | O71: 1 | P71: Express | Q71: Yes | R71: Yes | S71: 5 | T71: Cash | U71: Weekly | V71: 45447 | W71: =Table1[[#This Row],[customer_purchase count]]+1 -> 6 | X71: =Table1[[#This Row],[customer_purchase count]]*Rules!$B$3 -> 298.82179 | Y71: =IF(Table1[[#This Row],[customer_subscription]]=1,"Subscribed","Not Subscribed") -> Subscribed
A72: 71 | B72: 22 | C72: Male | D72: 71 | E72: Belt | F72: Accessories | G72: 71 | H72: 284 | I72: 29 | J72: Alabama | K72: M | L72: Magenta | M72: Fall | N72: 4.2 | O72: 1 | P72: Express | Q72: Yes | R72: Yes | S72: 32 | T72: Debit Card | U72: Every 3 Months | V72: 45581 | W72: =Table1[[#This Row],[customer_purchase count]]+1 -> 33 | X72: =Table1[[#This Row],[customer_purchase count]]*Rules!$B$3 -> 1912.4595 | Y72: =IF(Table1[[#This Row],[customer_subscription]]=1,"Subscribed","Not Subscribed") -> Subscribed
A73: 72 | B73: 36 | C73: Male | D73: 72 | E73: Dress | F73: Clothing | G73: 72 | H73: 285 | I73: 48 | J73: Virginia | K73: L | L73: Gold | M73: Summer | N73: 2.9 | O73: 1 | P73: Express | Q73: Yes | R73: Yes | S73: 34 | T73: Bank Transfer | U73: Annually | V73: 45483 | W73: =Table1[[#This Row],[customer_purchase count]]+1 -> 35 | X73: =Table1[[#This Row],[customer_purchase count]]*Rules!$B$3 -> 2031.9882 | Y73: =IF(Table1[[#This Row],[customer_subscription]]=1,"Subscribed","Not Subscribed") -> Subscribed | Z73: Loyal High Spenders
A74: 73 | B74: 18 | C74: Male | D74: 73 | E74: Dress | F74: Clothing | G74: 73 | H74: 286 | I74: 26 | J74: Georgia | K74: M | L74: Olive | M74: Winter | N74: 2.9 | O74: 1 | P74: Store Pickup | Q74: Yes | R74: Yes | S74: 21 | T74: Bank Transfer | U74: Every 3 Months | V74: 45344 | W74: =Table1[[#This Row],[customer_purchase count]]+1 -> 22 | X74: =Table1[[#This Row],[customer_purchase count]]*Rules!$B$3 -> 1255.0515 | Y74: =IF(Table1[[#This Row],[customer_subscription]]=1,"Subscribed","Not Subscribed") -> Subscribed
A75: 74 | B75: 48 | C75: Male | D75: 74 | E75: Pants | F75: Clothing | G75: 74 | H75: 287 | I75: 85 | J75: Hawaii | K75: M | L75: Teal | M75: Spring | N75: 2.7 | O75: 1 | P75: Free Shipping | Q75: Yes | R75: Yes | S75: 43 | T75: Bank Transfer | U75: Bi-Weekly | V75: 45405 | W75: =Table1[[#This Row],[customer_purchase count]]+1 -> 44 | X75: =Table1[[#This Row],[customer_purchase count]]*Rules!$B$3 -> 2569.8674 | Y75: =IF(Table1[[#This Row],[customer_subscription]]=1,"Subscribed","Not Subscribed") -> Subscribed | Z75: Loyal High Spenders
A76: 75 | B76: 49 | C76: Male | D76: 75 | E76: Gloves | F76: Accessories | G76: 75 | H76: 289 | I76: 58 | J76: Indiana | K76: L | L76: Violet | M76: Spring | N76: 4.5 | O76: 1 | P76: Express | Q76: Yes | R76: Yes | S76: 3 | T76: Cash | U76: Monthly | V76: 45415 | W76: =Table1[[#This Row],[customer_purchase count]]+1 -> 4 | X76: =Table1[[#This Row],[customer_purchase count]]*Rules!$B$3 -> 179.29308 | Y76: =IF(Table1[[#This Row],[customer_subscription]]=1,"Subscribed","Not Subscribed") -> Subscribed
A77: 76 | B77: 64 | C77: Male | D77: 76 | E77: Scarf | F77: Accessories | G77: 76 | H77: 290 | I77: 85 | J77: Utah | K77: M | L77: Blue | M77: Summer | N77: 2.7 | O77: 1 | P77: Free Shipping | Q77: Yes | R77: Yes | S77: 21 | T77: Credit Card | U77: Annually | V77: 45449 | W77: =Table1[[#This Row],[customer_purchase count]]+1 -> 22 | X77: =Table1[[#This Row],[customer_purchase count]]*Rules!$B$3 -> 1255.0515 | Y77: =IF(Table1[[#This Row],[customer_subscription]]=1,"Subscribed","Not Subscribed") -> Subscribed
A78: 77 | B78: 50 | C78: Male | D78: 77 | E78: Hat | F78: Accessories | G78: 77 | H78: 291 | I78: 43 | J78: Delaware | K78: S | L78: Teal | M78: Summer | N78: 4.2 | O78: 1 | P78: Free Shipping | Q78: Yes | R78: Yes | S78: 32 | T78: Venmo | U78: Monthly | V78: 45510 | W78: =Table1[[#This Row],[customer_purchase count]]+1 -> 33 | X78: =Table1[[#This Row],[customer_purchase count]]*Rules!$B$3 -> 1912.4595 | Y78: =IF(Table1[[#This Row],[customer_subscription]]=1,"Subscribed","Not Subscribed") -> Subscribed
A79: 78 | B79: 22 | C79: Male | D79: 78 | E79: Dress | F79: Clothing | G79: 78 | H79: 292 | I79: 53 | J79: Delaware | K79: L | L79: Gold | M79: Summer | N79: 3.3 | O79: 1 | P79: Next Day Air | Q79: Yes | R79: Yes | S79: 36 | T79: Debit Card | U79: Fortnightly | V79: 45455 | W79: =Table1[[#This Row],[customer_purchase count]]+1 -> 37 | X79: =Table1[[#This Row],[customer_purchase count]]*Rules!$B$3 -> 2151.5169 | Y79: =IF(Table1[[#This Row],[customer_subscription]]=1,"Subscribed","Not Subscribed") -> Subscribed
A80: 79 | B80: 50 | C80: Male | D80: 79 | E80: Skirt | F80: Clothing | G80: 79 | H80: 293 | I80: 91 | J80: Nebraska | K80: M | L80: Maroon | M80: Spring | N80: 4.7 | O80: 1 | P80: Free Shipping | Q80: Yes | R80: Yes | S80: 50 | T80: Venmo | U80: Fortnightly | V80: 45405 | W80: =Table1[[#This Row],[customer_purchase count]]+1 -> 51 | X80: =Table1[[#This Row],[customer_purchase count]]*Rules!$B$3 -> 2988.2179 | Y80: =IF(Table1[[#This Row],[customer_subscription]]=1,"Subscribed","Not Subscribed") -> Subscribed | Z80: Loyal High Spenders
A81: 80 | B81: 38 | C81: Male | D81: 80 | E81: Jacket | F81: Outerwear | G81: 80 | H81: 295 | I81: 96 | J81: Iowa | K81: M | L81: Olive | M81: Winter | N81: 2.6 | O81: 1 | P81: 2-Day Shipping | Q81: Yes | R81: Yes | S81: 43 | T81: Bank Transfer | U81: Every 3 Months | V81: 45629 | W81: =Table1[[#This Row],[customer_purchase count]]+1 -> 44 | X81: =Table1[[#This Row],[customer_purchase count]]*Rules!$B$3 -> 2569.8674 | Y81: =IF(Table1[[#This Row],[customer_subscription]]=1,"Subscribed","Not Subscribed") -> Subscribed | Z81: Loyal High Spenders
A82: 81 | B82: 19 | C82: Male | D82: 81 | E82: Sandals | F82: Footwear | G82: 81 | H82: 296 | I82: 72 | J82: New York | K82: XL | L82: Blue | M82: Summer | N82: 3.3 | O82: 1 | P82: Store Pickup | Q82: Yes | R82: Yes | S82: 24 | T82: Credit Card | U82: Every 3 Months | V82: 45474 | W82: =Table1[[#This Row],[customer_purchase count]]+1 -> 25 | X82: =Table1[[#This Row],[customer_purchase count]]*Rules!$B$3 -> 1434.3446 | Y82: =IF(Table1[[#This Row],[customer_subscription]]=1,"Subscribed","Not Subscribed") -> Subscribed
A83: 82 | B83: 67 | C83: Male | D83: 82 | E83: Shoes | F83: Footwear | G83: 82 | H83: 297 | I83: 96 | J83: Virginia | K83: L | L83: Maroon | M83: Summer | N83: 2.6 | O83: 1 | P83: Express | Q83: Yes | R83: Yes | S83: 36 | T83: Credit Card | U83: Every 3 Months | V83: 45518 | W83: =Table1[[#This Row],[customer_purchase count]]+1 -> 37 | X83: =Table1[[#This Row],[customer_purchase count]]*Rules!$B$3 -> 2151.5169 | Y83: =IF(Table1[[#This Row],[customer_subscription]]=1,"Subscribed","Not Subscribed") -> Subscribed
A84: 83 | B84: 19 | C84: Male | D84: 83 | E84: Pants | F84: Clothing | G84: 83 | H84: 298 | I84: 28 | J84: Georgia | K84: S | L84: Olive | M84: Spring | N84: 4 | O84: 1 | P84: 2-Day Shipping | Q84: Yes | R84: Yes | S84: 21 | T84: Credit Card | U84: Every 3 Months | V84: 45367 | W84: =Table1[[#This Row],[customer_purchase count]]+1 -> 22 | X84: =Table1[[#This Row],[customer_purchase count]]*Rules!$B$3 -> 1255.0515 | Y84: =IF(Table1[[#This Row],[customer_subscription]]=1,"Subscribed","Not Subscribed") -> Subscribed
A85: 84 | B85: 36 | C85: Male | D85: 84 | E85: Dress | F85: Clothing | G85: 84 | H85: 299 | I85: 40 | J85: Texas | K85: M | L85: Turquoise | M85: Summer | N85: 4.1 | O85: 1 | P85: Standard | Q85: Yes | R85: Yes | S85: 34 | T85: Bank Transfer | U85: Weekly | V85: 45506 | W85: =Table1[[#This Row],[customer_purchase count]]+1 -> 35 | X85: =Table1[[#This Row],[customer_purchase count]]*Rules!$B$3 -> 2031.9882 | Y85: =IF(Table1[[#This Row],[customer_subscription]]=1,"Subscribed","Not Subscribed") -> Subscribed | Z85: Loyal High Spenders
A86: 85 | B86: 52 | C86: Male | D86: 85 | E86: Coat | F86: Outerwear | G86: 85 | H86: 301 | I86: 32 | J86: Arizona | K86: S | L86: Peach | M86: Spring | N86: 4.4 | O86: 1 | P86: Standard | Q86: Yes | R86: Yes | S86: 42 | T86: Bank Transfer | U86: Every 3 Months | V86: 45366 | W86: =Table1[[#This Row],[customer_purchase count]]+1 -> 43 | X86: =Table1[[#This Row],[customer_purchase count]]*Rules!$B$3 -> 2510.1031 | Y86: =IF(Table1[[#This Row],[customer_subscription]]=1,"Subscribed","Not Subscribed") -> Subscribed | Z86: Loyal High Spenders
A87: 86 | B87: 53 | C87: Male | D87: 86 | E87: Sunglasses | F87: Accessories | G87: 86 | H87: 302 | I87: 95 | J87: New Mexico | K87: M | L87: Charcoal | M87: Winter | N87: 4.5 | O87: 1 | P87: Next Day Air | Q87: Yes | R87: Yes | S87: 2 | T87: Debit Card | U87: Bi-Weekly | V87: 45649 | W87: =Table1[[#This Row],[customer_purchase count]]+1 -> 3 | X87: =Table1[[#This Row],[customer_purchase count]]*Rules!$B$3 -> 119.52872 | Y87: =IF(Table1[[#This Row],[customer_subscription]]=1,"Subscribed","Not Subscribed") -> Subscribed
A88: 87 | B88: 24 | C88: Male | D88: 87 | E88: Hoodie | F88: Clothing | G88: 87 | H88: 303 | I88: 41 | J88: Nevada | K88: L | L88: Pink | M88: Spring | N88: 3.7 | O88: 1 | P88: 2-Day Shipping | Q88: Yes | R88: Yes | S88: 47 | T88: Cash | U88: Bi-Weekly | V88: 45399 | W88: =Table1[[#This Row],[customer_purchase count]]+1 -> 48 | X88: =Table1[[#This Row],[customer_purchase count]]*Rules!$B$3 -> 2808.9249 | Y88: =IF(Table1[[#This Row],[customer_subscription]]=1,"Subscribed","Not Subscribed") -> Subscribed
A89: 88 | B89: 52 | C89: Male | D89: 88 | E89: Shoes | F89: Footwear | G89: 88 | H89: 304 | I89: 53 | J89: Ohio | K89: M | L89: Green | M89: Fall | N89: 3.7 | O89: 1 | P89: 2-Day Shipping | Q89: Yes | R89: Yes | S89: 44 | T89: Debit Card | U89: Fortnightly | V89: 45536 | W89: =Table1[[#This Row],[customer_purchase count]]+1 -> 45 | X89: =Table1[[#This Row],[customer_purchase count]]*Rules!$B$3 -> 2629.6318 | Y89: =IF(Table1[[#This Row],[customer_subscription]]=1,"Subscribed","Not Subscribed") -> Subscribed | Z89: Loyal High Spenders
A90: 89 | B90: 33 | C90: Male | D90: 89 | E90: T-shirt | F90: Clothing | G90: 89 | H90: 305 | I90: 47 | J90: Wyoming | K90: M | L90: Orange | M90: Fall | N90: 3.5 | O90: 1 | P90: Free Shipping | Q90: Yes | R90: Yes | S90: 35 | T90: Credit Card | U90: Monthly | V90: 45589 | W90: =Table1[[#This Row],[customer_purchase count]]+1 -> 36 | X90: =Table1[[#This Row],[customer_purchase count]]*Rules!$B$3 -> 2091.7526 | Y90: =IF(Table1[[#This Row],[customer_subscription]]=1,"Subscribed","Not Subscribed") -> Subscribed | Z90: Loyal High Spenders
A91: 90 | B91: 47 | C91: Male | D91: 90 | E91: Jacket | F91: Outerwear | G91: 90 | H91: 307 | I91: 83 | J91: California | K91: XL | L91: Pink | M91: Fall | N91: 3.6 | O91: 1 | P91: Next Day Air | Q91: Yes | R91: Yes | S91: 15 | T91: Cash | U91: Quarterly | V91: 45571 | W91: =Table1[[#This Row],[customer_purchase count]]+1 -> 16 | X91: =Table1[[#This Row],[customer_purchase count]]*Rules!$B$3 -> 896.46538 | Y91: =IF(Table1[[#This Row],[customer_subscription]]=1,"Subscribed","Not Subscribed") -> Subscribed
A92: 91 | B92: 25 | C92: Male | D92: 91 | E92: Hat | F92: Accessories | G92: 91 | H92: 308 | I92: 48 | J92: South Carolina | K92: L | L92: Violet | M92: Summer | N92: 2.9 | O92: 1 | P92: Express | Q92: Yes | R92: Yes | S92: 29 | T92: Credit Card | U92: Monthly | V92: 45496 | W92: =Table1[[#This Row],[customer_purchase count]]+1 -> 30 | X92: =Table1[[#This Row],[customer_purchase count]]*Rules!$B$3 -> 1733.1664 | Y92: =IF(Table1[[#This Row],[customer_subscription]]=1,"Subscribed","Not Subscribed") -> Subscribed
A93: 92 | B93: 44 | C93: Male | D93: 92 | E93: Scarf | F93: Accessories | G93: 92 | H93: 309 | I93: 99 | J93: South Carolina | K93: S | L93: Green | M93: Winter | N93: 4.6 | O93: 1 | P93: Standard | Q93: Yes | R93: Yes | S93: 18 | T93: Credit Card | U93: Every 3 Months | V93: 45305 | W93: =Table1[[#This Row],[customer_purchase count]]+1 -> 19 | X93: =Table1[[#This Row],[customer_purchase count]]*Rules!$B$3 -> 1075.7585 | Y93: =IF(Table1[[#This Row],[customer_subscription]]=1,"Subscribed","Not Subscribed") -> Subscribed
A94: 93 | B94: 61 | C94: Male | D94: 93 | E94: Jacket | F94: Outerwear | G94: 93 | H94: 310 | I94: 87 | J94: Texas | K94: M | L94: Olive | M94: Winter | N94: 4.4 | O94: 1 | P94: 2-Day Shipping | Q94: Yes | R94: Yes | S94: 13 | T94: Venmo | U94: Every 3 Months | V94: 45640 | W94: =Table1[[#This Row],[customer_purchase count]]+1 -> 14 | X94: =Table1[[#This Row],[customer_purchase count]]*Rules!$B$3 -> 776.93667 | Y94: =IF(Table1[[#This Row],[customer_subscription]]=1,"Subscribed","Not Subscribed") -> Subscribed
A95: 94 | B95: 37 | C95: Male | D95: 94 | E95: Sweater | F95: Clothing | G95: 94 | H95: 311 | I95: 62 | J95: Florida | K95: M | L95: Purple | M95: Fall | N95: 4.5 | O95: 1 | P95: Standard | Q95: Yes | R95: Yes | S95: 46 | T95: Credit Card | U95: Weekly | V95: 45614 | W95: =Table1[[#This Row],[customer_purchase count]]+1 -> 47 | X95: =Table1[[#This Row],[customer_purchase count]]*Rules!$B$3 -> 2749.1605 | Y95: =IF(Table1[[#This Row],[customer_subscription]]=1,"Subscribed","Not Subscribed") -> Subscribed | Z95: Loyal High Spenders
A96: 95 | B96: 58 | C96: Male | D96: 95 | E96: Skirt | F96: Clothing | G96: 95 | H96: 313 | I96: 76 | J96: Nevada | K96: S | L96: Silver | M96: Spring | N96: 4.6 | O96: 1 | P96: Free Shipping | Q96: Yes | R96: Yes | S96: 28 | T96: Credit Card | U96: Weekly | V96: 45394 | W96: =Table1[[#This Row],[customer_purchase count]]+1 -> 29 | X96: =Table1[[#This Row],[customer_purchase count]]*Rules!$B$3 -> 1673.4021 | Y96: =IF(Table1[[#This Row],[customer_subscription]]=1,"Subscribed","Not Subscribed") -> Subscribed
A97: 96 | B97: 37 | C97: Male | D97: 96 | E97: Sneakers | F97: Footwear | G97: 96 | H97: 314 | I97: 100 | J97: Missouri | K97: L | L97: Pink | M97: Fall | N97: 3.8 | O97: 1 | P97: Free Shipping | Q97: Yes | R97: Yes | S97: 48 | T97: PayPal | U97: Monthly | V97: 45568 | W97: =Table1[[#This Row],[customer_purchase count]]+1 -> 49 | X97: =Table1[[#This Row],[customer_purchase count]]*Rules!$B$3 -> 2868.6892 | Y97: =IF(Table1[[#This Row],[customer_subscription]]=1,"Subscribed","Not Subscribed") -> Subscribed | Z97: Loyal High Spenders
A98: 97 | B98: 32 | C98: Male | D98: 97 | E98: Gloves | F98: Accessories | G98: 97 | H98: 315 | I98: 73 | J98: Delaware | K98: S | L98: Gold | M98: Spring | N98: 3.6 | O98: 1 | P98: Express | Q98: Yes | R98: Yes | S98: 43 | T98: Venmo | U98: Every 3 Months | V98: 45438 | W98: =Table1[[#This Row],[customer_purchase count]]+1 -> 44 | X98: =Table1[[#This Row],[customer_purchase count]]*Rules!$B$3 -> 2569.8674 | Y98: =IF(Table1[[#This Row],[customer_subscription]]=1,"Subscribed","Not Subscribed") -> Subscribed | Z98: Loyal High Spenders
A99: 98 | B99: 21 | C99: Male | D99: 98 | E99: Shoes | F99: Footwear | G99: 98 | H99: 316 | I99: 92 | J99: Virginia | K99: M | L99: Teal | M99: Winter | N99: 4.8 | O99: 1 | P99: Store Pickup | Q99: Yes | R99: Yes | S99: 37 | T99: Cash | U99: Annually | V99: 45326 | W99: =Table1[[#This Row],[customer_purchase count]]+1 -> 38 | X99: =Table1[[#This Row],[customer_purchase count]]*Rules!$B$3 -> 2211.2813 | Y99: =IF(Table1[[#This Row],[customer_subscription]]=1,"Subscribed","Not Subscribed") -> Subscribed
A100: 99 | B100: 20 | C100: Male | D100: 99 | E100: Jeans | F100: Clothing | G100: 99 | H100: 317 | I100: 67 | J100: New York | K100: XL | L100: Teal | M100: Spring | N100: 2.6 | O100: 1 | P100: Next Day Air | Q100: Yes | R100: Yes | S100: 20 | T100: Bank Transfer | U100: Annually | V100: 45435 | W100: =Table1[[#This Row],[customer_purchase count]]+1 -> 21 | X100: =Table1[[#This Row],[customer_purchase count]]*Rules!$B$3 -> 1195.2872 | Y100: =IF(Table1[[#This Row],[customer_subscription]]=1,"Subscribed","Not Subscribed") -> Subscribed
A101: 100 | B101: 26 | C101: Male | D101: 100 | E101: Hoodie | F101: Clothing | G101: 100 | H101: 319 | I101: 40 | J101: Missouri | K101: XL | L101: Indigo | M101: Summer | N101: 3.7 | O101: 1 | P101: Express | Q101: Yes | R101: Yes | S101: 33 | T101: Debit Card | U101: Quarterly | V101: 45496 | W101: =Table1[[#This Row],[customer_purchase count]]+1 -> 34 | X101: =Table1[[#This Row],[customer_purchase count]]*Rules!$B$3 -> 1972.2238 | Y101: =IF(Table1[[#This Row],[customer_subscription]]=1,"Subscribed","Not Subscribed") -> Subscribed
A102: 101 | B102: 62 | C102: Male | D102: 101 | E102: Sunglasses | F102: Accessories | G102: 101 | H102: 320 | I102: 98 | J102: South Dakota | K102: M | L102: Maroon | M102: Fall | N102: 2.7 | O102: 1 | P102: Express | Q102: Yes | R102: Yes | S102: 31 | T102: Cash | U102: Fortnightly | V102: 45623 | W102: =Table1[[#This Row],[customer_purchase count]]+1 -> 32 | X102: =Table1[[#This Row],[customer_purchase count]]*Rules!$B$3 -> 1852.6951 | Y102: =IF(Table1[[#This Row],[customer_subscription]]=1,"Subscribed","Not Subscribed") -> Subscribed
A103: 102 | B103: 27 | C103: Male | D103: 102 | E103: Coat | F103: Outerwear | G103: 102 | H103: 321 | I103: 85 | J103: North Dakota | K103: XL | L103: White | M103: Spring | N103: 4.6 | O103: 1 | P103: Express | Q103: Yes | R103: Yes | S103: 50 | T103: Credit Card | U103: Bi-Weekly | V103: 45418 | W103: =Table1[[#This Row],[customer_purchase count]]+1 -> 51 | X103: =Table1[[#This Row],[customer_purchase count]]*Rules!$B$3 -> 2988.2179 | Y103: =IF(Table1[[#This Row],[customer_subscription]]=1,"Subscribed","Not Subscribed") -> Subscribed
A104: 103 | B104: 51 | C104: Male | D104: 103 | E104: Socks | F104: Clothing | G104: 103 | H104: 322 | I104: 67 | J104: Oklahoma | K104: L | L104: Violet | M104: Winter | N104: 4.8 | O104: 1 | P104: Next Day Air | Q104: Yes | R104: Yes | S104: 35 | T104: Credit Card | U104: Quarterly | V104: 45345 | W104: =Table1[[#This Row],[customer_purchase count]]+1 -> 36 | X104: =Table1[[#This Row],[customer_purchase count]]*Rules!$B$3 -> 2091.7526 | Y104: =IF(Table1[[#This Row],[customer_subscription]]=1,"Subscribed","Not Subscribed") -> Subscribed | Z104: Loyal High Spenders
...

Sheet Rules
A1: Column A | B1: Column B | C1: Column C
A2: Metric | B2: Value | C2: column Ref | G2: Personas | H2: Criteria | I2: Note | J2: Count | M2: Personas | N2: Customers | O2: Revenue | P2: ARPU
A3: Average of Purchase amount | B3: =AVERAGE(Table1[purchase_amount]) -> 59.764359 | C3: $B$3 | G3: Young Budget Shoppers | H3: Age < 30, Spend < Low Spend, Purchase Count > High Frequency | I3: total quantity between 10 and 18 | J3: 168 | M3: Young Budget Shoppers | N3: 168 | O3: 128493 | P3: =O3/N3 -> 764.83929
A4: Median Total Spend | B4: =MEDIAN(Table1[Total_Spend]) -> 1494.109 | C4: $B$4 | G4: Loyal High Spenders | H4: Age between 36–60, Spend > High Spend, Subscribed | J4: 158 | M4: Loyal High Spenders | N4: 230 | O4: 569076 | P4: =O4/N4 -> 2474.2435
A5: Stdev Total Spend | B5: =STDEV(Table1[Total_Spend]) -> 863.42317 | C5: $B$5 | G5: Occasional Deal Seekers | H5: Purchase Count < Low Frequency, Spend < Low, Unsubscribed | J5: 858 | M5: Occasional Deal Seekers | N5: 858 | O5: 413151 | P5: =O5/N5 -> 481.52797
A6: Median Total Purchase Count | B6: =MEDIAN(Table1[Total_Purchase_Count]) -> 26 | C6: $B$6
A7: STDEV Total Purchase Count | B7: =STDEV(Table1[Total_Purchase_Count]) -> 14.447125 | C7: $B$7
A9: Low Spend | B9: =B4- 0.5*B5 -> 1062.3974 | C9: $B$9
A10: High Spend | B10: =B4+0.5*B5 -> 1925.8206 | C10: $B$10
A11: Moderate spend | B11: between above two
A12: Low Frequency | B12: =B6-0.5*B7 -> 18.776437 | C12: $B$12
A13: High Frequency | B13: =B6+0.5*B7 -> 33.223563 | C13: $B$13
A15: Low limit | B15: Median - 0.5*STDEV
A16: High Limit | B16: Median + 0.5*STDEV
